Metadata-Version: 2.4
Name: PyHydroGeophysX
Version: 0.1.0
Summary: A comprehensive Python package for integrating hydrological model outputs with geophysical forward modeling and inversion
Home-page: https://github.com/geohang/PyHydroGeophysX
Author: Hang Chen
Author-email: Hang Chen <hangchen.work@gmail.com>
License: MIT
Project-URL: Homepage, https://github.com/geohang/PyHydroGeophysX
Project-URL: Documentation, https://geohang.github.io/PyHydroGeophysX/
Project-URL: Repository, https://github.com/geohang/PyHydroGeophysX
Project-URL: Bug Tracker, https://github.com/geohang/PyHydroGeophysX/issues
Keywords: geophysics,hydrology,ERT,seismic,tomography,inversion,MODFLOW,ParFlow,watershed monitoring
Classifier: Development Status :: 3 - Alpha
Classifier: Intended Audience :: Science/Research
Classifier: Topic :: Scientific/Engineering :: Hydrology
Classifier: Topic :: Scientific/Engineering :: Physics
Classifier: License :: OSI Approved :: MIT License
Classifier: Operating System :: OS Independent
Classifier: Programming Language :: Python :: 3
Classifier: Programming Language :: Python :: 3.8
Classifier: Programming Language :: Python :: 3.9
Classifier: Programming Language :: Python :: 3.10
Classifier: Programming Language :: Python :: 3.11
Classifier: Programming Language :: Python :: 3.12
Requires-Python: >=3.8
License-File: LICENSE
Requires-Dist: numpy>=1.19
Requires-Dist: scipy>=1.5
Requires-Dist: matplotlib>=3.2
Requires-Dist: tqdm>=4.0
Provides-Extra: geophysics
Requires-Dist: pygimli>=1.5; extra == "geophysics"
Requires-Dist: flopy; extra == "geophysics"
Requires-Dist: joblib; extra == "geophysics"
Provides-Extra: gpu
Requires-Dist: cupy; extra == "gpu"
Provides-Extra: dev
Requires-Dist: pytest>=6.0; extra == "dev"
Requires-Dist: pytest-cov; extra == "dev"
Requires-Dist: black; extra == "dev"
Requires-Dist: flake8; extra == "dev"
Provides-Extra: all
Requires-Dist: pygimli>=1.5; extra == "all"
Requires-Dist: flopy; extra == "all"
Requires-Dist: joblib; extra == "all"
Requires-Dist: cupy; extra == "all"
Requires-Dist: pytest>=6.0; extra == "all"
Requires-Dist: pytest-cov; extra == "all"
Requires-Dist: black; extra == "all"
Requires-Dist: flake8; extra == "all"
Dynamic: author
Dynamic: home-page
Dynamic: license-file
Dynamic: requires-python
